Metadata-Version: 1.2
Name: django-polls-drvl
Version: 0.0.1
Summary: "A Django app to conduct Web-based polls."
Home-page: https://www.example.com/
Author: Durval Carvalho
Author-email: durval@gmail.com
License: "BSD-3-Clause"
Platform: UNKNOWN
Classifier: Environment :: Web Environment
Classifier: Framework :: Django
Classifier: Framework :: Django :: 3.2
Classifier: Intended Audience :: Developers
Classifier: License :: OSI Approved :: BSD License
Classifier: Operating System :: OS Independent
Classifier: Programming Language :: Python
Classifier: Programming Language :: Python :: 3
Classifier: Programming Language :: Python :: 3.8
Classifier: Topic :: Internet :: WWW/HTTP
Classifier: Topic :: Internet :: WWW/HTTP :: Dynamic Content
Requires-Python: >=3.8
